bmopentracing/__init__.py
bmopentracing/middlewares/__init__.py
bmopentracing/middlewares/fastapi/__init__.py
bmopentracing/middlewares/flask/__init__.py
bmopentracing/tracers/__init__.py
bmopentracing/tracers/jaeger/__init__.py
bmopentracing/tracers/jaeger/tracer.py
bmopentracing-0.0.7.dist-info/LICENSE
bmopentracing-0.0.7.dist-info/METADATA
bmopentracing-0.0.7.dist-info/WHEEL
bmopentracing-0.0.7.dist-info/top_level.txt
bmopentracing-0.0.7.dist-info/RECORD
